<Defs xmlns:xsi="http://www.w3.org/2001/XMLSchema-instance" xsi:noNamespaceSchemaLocation= "https://raw.githubusercontent.com/Tachyonite/Pawnmorpher/dev/Schemas/MutationDef.xsd">
	<Pawnmorph.Hediffs.MutationDef ParentName="WildBovidJawPart">
		<classInfluence>PMAE_WildebeestMorph</classInfluence>
		<defName>PMAE_WildebeestJaw</defName>
		<label>wildebeest snout</label>
		<graphics>
			<MuzzleMale>Parts/Wildebeest/Wildebeest_Muzzle_Male</MuzzleMale>
			<MuzzleFemale>Parts/Wildebeest/Wildebeest_Muzzle_Female</MuzzleFemale>
		</graphics>
	</Pawnmorph.Hediffs.MutationDef>
	
		<Pawnmorph.Hediffs.MutationDef ParentName="WildBovidEarPart">
		<classInfluence>PMAE_WildebeestMorph</classInfluence>
		<defName>PMAE_WildebeestEar</defName>
		<label>wildebeest ear</label>
		<graphics>
			<LeftEar>Parts/Wildebeest/Wildebeest_Ear_Left</LeftEar>
			<LeftEarBehind>Parts/None/None</LeftEarBehind>
			<RightEar>Parts/Wildebeest/Wildebeest_Ear_Right</RightEar>
			<RightEarBehindHead>Parts/None/None</RightEarBehindHead>
		</graphics>
		<stagePatches>
			<li function="modify">
				<stageKey>grown</stageKey>
				<values>
					<description>TODO Wildebeest</description>
				</values>
			</li>
		</stagePatches>
	</Pawnmorph.Hediffs.MutationDef>

	<Pawnmorph.Hediffs.MutationDef ParentName="WildBovidTailPart">
		<classInfluence>PMAE_WildebeestMorph</classInfluence>
		<defName>PMAE_WildebeestTail</defName>
		<label>wildebeest tail</label>
		<graphics>
			<Tail>Parts/Wildebeest/Wildebeest_Tail</Tail>
		</graphics>
		<stagePatches>
			<li function="modify">
				<stageKey>grown</stageKey>
				<values>
					<description>TODO Wildebeest</description>
				</values>
			</li>
		</stagePatches>
	</Pawnmorph.Hediffs.MutationDef>

	<Pawnmorph.Hediffs.MutationDef ParentName="WildBovidHornPart">
		<defName>EtherWildebeestHorns</defName>
		<classInfluence>PMAE_WildebeestMorph</classInfluence>
		<label>horns</label>
		<description>A pair of wildebeest horns.</description>
		<graphics>
			<Horns>Parts/Wildebeest/Wildebeest_Horns_C</Horns>
		</graphics>
		<!-- <mutationTale>TODO</mutationTale>
		<mutationMemory>TODO</mutationMemory> -->
		<stagePatches>
			<li function="modify">
				<stageKey>nubs</stageKey>
				<values>
					<graphics>
						<Horns>Parts/Wildebeest/Wildebeest_Horns_A</Horns>
					</graphics>
				</values>
			</li>
			<li function="modify">
				<stageKey>short</stageKey>
				<values>
					<description>Curved horns decorate [PAWN_nameDef]'s head, which can easily be used to stab and puncture anyone foolish enough to tussle with [PAWN_nameDef]. They have grown larger, but still have a little more growing to do.</description>
					<graphics>
						<Horns>Parts/Wildebeest/Wildebeest_Horns_B</Horns>
					</graphics>
				</values>
			</li>
			<li function="modify">
				<stageKey>horns</stageKey>
				<values>
					<description>Two short horns grow from the sides of [PAWN_nameDef]'s head. They're sharp and dangerous to get near if [PAWN_nameDef] happened to be in a bad mood.</description>
					<graphics>
						<Horns>Parts/Wildebeest/Wildebeest_Horns_C</Horns>
					</graphics>
				</values>
			</li>
		</stagePatches>
	
	</Pawnmorph.Hediffs.MutationDef>
	
</Defs>
